{
  "enabled": true,
  "next_event_time": "2026-03-25T23:30:00+00:00",
  "last_event_time": "2026-03-24T22:00:00+00:00",
  "last_boundary_time": "2026-03-20T20:30:17+00:00",
  "links": {},
  "history": [
    {
      "event_time": "2026-03-21T07:26:11.405657+00:00",
      "cycle_started_at": "2026-03-21T07:26:00.833293+00:00",
      "winner_username": null,
      "winner_points": null,
      "eligible_match_count": 0
    },
    {
      "event_time": "2026-03-21T09:47:58+00:00",
      "cycle_started_at": "2026-03-21T07:26:11.405657+00:00",
      "winner_username": "tv999",
      "winner_points": 49.24,
      "eligible_match_count": 5
    },
    {
      "event_time": "2026-03-22T05:00:00+00:00",
      "cycle_started_at": "2026-03-21T09:47:58+00:00",
      "winner_username": "URMB4",
      "winner_points": 88.44,
      "eligible_match_count": 5
    },
    {
      "event_time": "2026-03-23T20:30:00+00:00",
      "cycle_started_at": "2026-03-22T05:00:00+00:00",
      "winner_username": "Z2Yfi",
      "winner_points": 116.06,
      "eligible_match_count": 12
    },
    {
      "event_time": "2026-03-24T22:00:00+00:00",
      "cycle_started_at": "2026-03-23T20:30:00+00:00",
      "winner_username": "vt2Mr",
      "winner_points": 209.41,
      "eligible_match_count": 14
    }
  ],
  "last_seen_time": "2026-03-25T08:57:47+00:00",
  "current_scores": {
    "9mvRT": {
      "points": 11.24,
      "match_count": 1,
      "last_score_time": "2026-03-24T22:37:42+00:00"
    },
    "GueSH": {
      "points": 10.39,
      "match_count": 1,
      "last_score_time": "2026-03-24T22:37:42+00:00"
    },
    "vnIqS": {
      "points": 5.35,
      "match_count": 1,
      "last_score_time": "2026-03-24T22:37:42+00:00"
    },
    "4lfdj": {
      "points": 0.02,
      "match_count": 1,
      "last_score_time": "2026-03-24T22:37:42+00:00"
    },
    "rY4UW": {
      "points": 27.32,
      "match_count": 1,
      "last_score_time": "2026-03-25T04:45:37+00:00"
    },
    "b92M9": {
      "points": 18.49,
      "match_count": 1,
      "last_score_time": "2026-03-25T04:45:37+00:00"
    },
    "9B9B9": {
      "points": 15.87,
      "match_count": 1,
      "last_score_time": "2026-03-25T04:45:37+00:00"
    },
    "LMrbr": {
      "points": 13.0,
      "match_count": 1,
      "last_score_time": "2026-03-25T04:45:37+00:00"
    },
    "rn5v7": {
      "points": 11.17,
      "match_count": 1,
      "last_score_time": "2026-03-25T04:45:37+00:00"
    },
    "Yb0bR": {
      "points": 8.83,
      "match_count": 1,
      "last_score_time": "2026-03-25T04:45:37+00:00"
    },
    "BNxHu": {
      "points": 31.39,
      "match_count": 2,
      "last_score_time": "2026-03-25T06:18:42+00:00"
    },
    "pGdHc": {
      "points": 7.16,
      "match_count": 1,
      "last_score_time": "2026-03-25T04:45:37+00:00"
    },
    "VNnLm": {
      "points": 6.28,
      "match_count": 1,
      "last_score_time": "2026-03-25T04:45:37+00:00"
    },
    "rNR7n": {
      "points": 2.39,
      "match_count": 1,
      "last_score_time": "2026-03-25T04:45:37+00:00"
    },
    "YsRY1": {
      "points": 5.43,
      "match_count": 2,
      "last_score_time": "2026-03-25T07:32:35+00:00"
    },
    "q7qn5": {
      "points": 1.81,
      "match_count": 1,
      "last_score_time": "2026-03-25T04:45:37+00:00"
    },
    "QQMb8": {
      "points": 1.12,
      "match_count": 1,
      "last_score_time": "2026-03-25T04:45:37+00:00"
    },
    "bMRN5": {
      "points": 0.67,
      "match_count": 1,
      "last_score_time": "2026-03-25T04:45:37+00:00"
    },
    "tv999": {
      "points": 60.01,
      "match_count": 3,
      "last_score_time": "2026-03-25T08:57:47+00:00"
    },
    "TmL85": {
      "points": 23.95,
      "match_count": 1,
      "last_score_time": "2026-03-25T06:18:42+00:00"
    },
    "WWREy": {
      "points": 21.01,
      "match_count": 1,
      "last_score_time": "2026-03-25T06:18:42+00:00"
    },
    "k2zdq": {
      "points": 6.53,
      "match_count": 1,
      "last_score_time": "2026-03-25T06:18:42+00:00"
    },
    "VBmV2": {
      "points": 6.14,
      "match_count": 1,
      "last_score_time": "2026-03-25T06:18:42+00:00"
    },
    "D46hN": {
      "points": 3.53,
      "match_count": 1,
      "last_score_time": "2026-03-25T06:18:42+00:00"
    },
    "2727M": {
      "points": 3.35,
      "match_count": 1,
      "last_score_time": "2026-03-25T06:18:42+00:00"
    },
    "8nqVN": {
      "points": 141.99,
      "match_count": 1,
      "last_score_time": "2026-03-25T06:30:19+00:00"
    },
    "nTnTt": {
      "points": 46.49,
      "match_count": 1,
      "last_score_time": "2026-03-25T07:32:35+00:00"
    },
    "qmLtT": {
      "points": 3.41,
      "match_count": 1,
      "last_score_time": "2026-03-25T07:32:35+00:00"
    },
    "mv5M7": {
      "points": 0.86,
      "match_count": 1,
      "last_score_time": "2026-03-25T07:32:35+00:00"
    },
    "Z2Yfi": {
      "points": 31.0,
      "match_count": 1,
      "last_score_time": "2026-03-25T07:44:22+00:00"
    },
    "tb7qT": {
      "points": 25.92,
      "match_count": 1,
      "last_score_time": "2026-03-25T07:51:21+00:00"
    },
    "NO2uX": {
      "points": 6.06,
      "match_count": 1,
      "last_score_time": "2026-03-25T07:51:21+00:00"
    },
    "7r9Rb": {
      "points": 2.86,
      "match_count": 1,
      "last_score_time": "2026-03-25T07:51:21+00:00"
    },
    "xAfz7": {
      "points": 1.16,
      "match_count": 1,
      "last_score_time": "2026-03-25T07:51:21+00:00"
    },
    "yzbhH": {
      "points": 27.23,
      "match_count": 1,
      "last_score_time": "2026-03-25T07:53:00+00:00"
    },
    "7mQLL": {
      "points": 2.77,
      "match_count": 1,
      "last_score_time": "2026-03-25T07:53:00+00:00"
    },
    "52B5N": {
      "points": 13.42,
      "match_count": 1,
      "last_score_time": "2026-03-25T08:57:47+00:00"
    },
    "V7QRR": {
      "points": 5.28,
      "match_count": 1,
      "last_score_time": "2026-03-25T08:57:47+00:00"
    },
    "N7Bb5": {
      "points": 5.03,
      "match_count": 1,
      "last_score_time": "2026-03-25T08:57:47+00:00"
    },
    "5t7Bt": {
      "points": 2.77,
      "match_count": 1,
      "last_score_time": "2026-03-25T08:57:47+00:00"
    },
    "vqLT5": {
      "points": 2.36,
      "match_count": 1,
      "last_score_time": "2026-03-25T08:57:47+00:00"
    },
    "rTrTL": {
      "points": 1.98,
      "match_count": 1,
      "last_score_time": "2026-03-25T08:57:47+00:00"
    },
    "fsjgX": {
      "points": 1.88,
      "match_count": 1,
      "last_score_time": "2026-03-25T08:57:47+00:00"
    },
    "v9rQM": {
      "points": 1.65,
      "match_count": 1,
      "last_score_time": "2026-03-25T08:57:47+00:00"
    },
    "tnvL7": {
      "points": 1.55,
      "match_count": 1,
      "last_score_time": "2026-03-25T08:57:47+00:00"
    },
    "B9mv9": {
      "points": 0.85,
      "match_count": 1,
      "last_score_time": "2026-03-25T08:57:47+00:00"
    },
    "r5m5T": {
      "points": 0.6,
      "match_count": 1,
      "last_score_time": "2026-03-25T08:57:47+00:00"
    },
    "rmLM9": {
      "points": 0.44,
      "match_count": 1,
      "last_score_time": "2026-03-25T08:57:47+00:00"
    },
    "L7vVb": {
      "points": 0.0,
      "match_count": 1,
      "last_score_time": "2026-03-25T08:57:47+00:00"
    }
  },
  "current_cycle_started_at": "2026-03-24T22:00:00+00:00",
  "current_cycle_match_count": 9
}
